quantworks/__init__.py
quantworks/bar.py
quantworks/barfeed/__init__.py
quantworks/barfeed/common.py
quantworks/barfeed/csvfeed.py
quantworks/barfeed/dbfeed.py
quantworks/barfeed/googlefeed.py
quantworks/barfeed/listfeed.py
quantworks/barfeed/membf.py
quantworks/barfeed/ninjatraderfeed.py
quantworks/barfeed/pandasfeed.py
quantworks/barfeed/quandlfeed.py
quantworks/barfeed/resampled.py
quantworks/barfeed/sqlitefeed.py
quantworks/barfeed/yahoofeed.py
quantworks/broker/__init__.py
quantworks/broker/backtesting.py
quantworks/broker/fillstrategy.py
quantworks/broker/slippage.py
quantworks/dataseries/__init__.py
quantworks/dataseries/aligned.py
quantworks/dataseries/bards.py
quantworks/dataseries/resampled.py
quantworks/dispatcher.py
quantworks/dispatchprio.py
quantworks/eventprofiler.py
quantworks/examples/__init__.py
quantworks/examples/sma_crossover.py
quantworks/feed/__init__.py
quantworks/feed/csvfeed.py
quantworks/feed/memfeed.py
quantworks/logger.py
quantworks/marketsession.py
quantworks/observer.py
quantworks/optimizer/__init__.py
quantworks/optimizer/base.py
quantworks/optimizer/local.py
quantworks/optimizer/serialization.py
quantworks/optimizer/server.py
quantworks/optimizer/worker.py
quantworks/optimizer/xmlrpcserver.py
quantworks/plotter.py
quantworks/resamplebase.py
quantworks/stratanalyzer/__init__.py
quantworks/stratanalyzer/drawdown.py
quantworks/stratanalyzer/returns.py
quantworks/stratanalyzer/sharpe.py
quantworks/stratanalyzer/trades.py
quantworks/strategy/__init__.py
quantworks/strategy/position.py
quantworks/talibext/__init__.py
quantworks/talibext/indicator.py
quantworks/technical/__init__.py
quantworks/technical/atr.py
quantworks/technical/bollinger.py
quantworks/technical/cross.py
quantworks/technical/cumret.py
quantworks/technical/highlow.py
quantworks/technical/hurst.py
quantworks/technical/linebreak.py
quantworks/technical/linreg.py
quantworks/technical/ma.py
quantworks/technical/macd.py
quantworks/technical/ratio.py
quantworks/technical/roc.py
quantworks-0.21.dist-info/LICENSE
quantworks-0.21.dist-info/WHEEL
quantworks-0.21.dist-info/METADATA
quantworks-0.21.dist-info/RECORD
