Metadata-Version: 2.1
Name: quantworks
Version: 0.21
Summary: Python Algorithmic Trading Framework
License: Apache-2.0
Author: Tyler M Kontra
Author-email: tyler@tylerkontra.com
Requires-Python: >=3.7,<4.0
Classifier: Development Status :: 3 - Alpha
Classifier: Intended Audience :: Developers
Classifier: Intended Audience :: Financial and Insurance Industry
Classifier: License :: OSI Approved :: Apache Software License
Classifier: Operating System :: OS Independent
Classifier: Programming Language :: Python :: 3
Classifier: Programming Language :: Python :: 3.7
Classifier: Programming Language :: Python :: 3.8
Classifier: Topic :: Office/Business :: Financial
Classifier: Topic :: Software Development :: Libraries :: Application Frameworks
Provides-Extra: TALib
Requires-Dist: TA-Lib (>=0.4.17,<0.5.0); extra == "TALib"
Requires-Dist: matplotlib (==3.1.2)
Requires-Dist: numpy (==1.18.0)
Requires-Dist: python-dateutil (==2.8.1)
Requires-Dist: pytz (==2019.3)
Requires-Dist: requests (==2.22.0)
Requires-Dist: retrying (==1.3.3)
Requires-Dist: scipy (==1.4.1)
Requires-Dist: six (==1.13.0)
Requires-Dist: tornado (==6.0.3)
Requires-Dist: ws4py (==0.3.4)
